HPV_TEAM_Dotcoin/HPV_Dotcoin.py
HPV_TEAM_Dotcoin/__init__.py
HPV_TEAM_Dotcoin-3.0.2.dist-info/METADATA
HPV_TEAM_Dotcoin-3.0.2.dist-info/WHEEL
HPV_TEAM_Dotcoin-3.0.2.dist-info/top_level.txt
HPV_TEAM_Dotcoin-3.0.2.dist-info/RECORD
